unscript/__init__.py
unscript/detect_script.py
unscript/ranges.py
unscript/script_ranges.py
unscript/unscript.py
unscript-0.1.3.dist-info/METADATA
unscript-0.1.3.dist-info/WHEEL
unscript-0.1.3.dist-info/licenses/LICENSE
unscript-0.1.3.dist-info/RECORD
