Metadata-Version: 2.4
Name: unscript
Version: 0.1.3
Summary: A writing script-aware library for cleaning text for NLP, training and analysis.
Project-URL: Homepage, https://github.com/omarkamali/unscript
Project-URL: Issues, https://github.com/omarkamali/unscript/issues
Author-email: Omar Kamali <unscript@omarkama.li>
License: MIT
License-File: LICENSE
Requires-Python: >=3.8
Provides-Extra: test
Requires-Dist: pytest>=7.0.0; extra == 'test'
